{
    "description": "This template can serve as common starting point for traceable analyses in observational clinical research. The project should get versioned, Identified, Linked, Documented, Tested, FAIR",
    "license": "GPL-3",
    "title": "Reproducible Clinical Research Project Template based on TRACE-RM",
    "upload_type": "software",
    "publication_date": "2020-11-22",
    "creators": [{
    "name": "Lukas Huber",
    "orcid": "0000-0001-5443-0290"
  }],
    "access_right": "open"
}
